fluffy/__init__.py
fluffy/app.py
fluffy/models.py
fluffy/run.py
fluffy/run_prod.py
fluffy/utils.py
fluffy/views.py
fluffy/component/__init__.py
fluffy/component/assets.py
fluffy/component/backends.py
fluffy/component/highlighting.py
fluffy/component/markdown.py
fluffy/component/styles.py
fluffy/static/app.css
fluffy/static/app.css.hash
fluffy/static/pygments.css
fluffy/static/pygments.css.hash
fluffy/static/img/favicon.ico
fluffy/static/img/favicon.ico.hash
fluffy/static/img/loading-32.gif
fluffy/static/img/loading-32.gif.hash
fluffy/static/img/mime/small/7z.png
fluffy/static/img/mime/small/7z.png.hash
fluffy/static/img/mime/small/README
fluffy/static/img/mime/small/README.hash
fluffy/static/img/mime/small/ai.png
fluffy/static/img/mime/small/ai.png.hash
fluffy/static/img/mime/small/bmp.png
fluffy/static/img/mime/small/bmp.png.hash
fluffy/static/img/mime/small/doc.png
fluffy/static/img/mime/small/doc.png.hash
fluffy/static/img/mime/small/docx.png
fluffy/static/img/mime/small/docx.png.hash
fluffy/static/img/mime/small/gif.png
fluffy/static/img/mime/small/gif.png.hash
fluffy/static/img/mime/small/gz.png
fluffy/static/img/mime/small/gz.png.hash
fluffy/static/img/mime/small/html.png
fluffy/static/img/mime/small/html.png.hash
fluffy/static/img/mime/small/jpeg.png
fluffy/static/img/mime/small/jpeg.png.hash
fluffy/static/img/mime/small/jpg.png
fluffy/static/img/mime/small/jpg.png.hash
fluffy/static/img/mime/small/midi.png
fluffy/static/img/mime/small/midi.png.hash
fluffy/static/img/mime/small/mp3.png
fluffy/static/img/mime/small/mp3.png.hash
fluffy/static/img/mime/small/odf.png
fluffy/static/img/mime/small/odf.png.hash
fluffy/static/img/mime/small/odt.png
fluffy/static/img/mime/small/odt.png.hash
fluffy/static/img/mime/small/paste-generic.png
fluffy/static/img/mime/small/paste-generic.png.hash
fluffy/static/img/mime/small/pdf.png
fluffy/static/img/mime/small/pdf.png.hash
fluffy/static/img/mime/small/png.png
fluffy/static/img/mime/small/png.png.hash
fluffy_server-1.40.1.dist-info/METADATA
fluffy_server-1.40.1.dist-info/WHEEL
fluffy_server-1.40.1.dist-info/entry_points.txt
fluffy_server-1.40.1.dist-info/licenses/LICENSE
fluffy_server-1.40.1.dist-info/RECORD
