Metadata-Version: 2.4
Name: fluffy-server
Version: 1.40.1
Author-email: Chris Kuehl <ckuehl@ckuehl.me>
License-Expression: Apache-2.0
License-File: LICENSE
Requires-Python: >=3.10
Requires-Dist: boto3
Requires-Dist: cached-property
Requires-Dist: csscompressor
Requires-Dist: flask
Requires-Dist: identify
Requires-Dist: mistune<0.999
Requires-Dist: pygments
Requires-Dist: pygments-ansi-color>=0.0.3
Requires-Dist: pygments-solarized-style
Requires-Dist: pyquery
